sc_log/ActivityOaLog.py
sc_log/ScLog.py
sc_log/__init__.py
get_sc_log-0.1.3.dist-info/METADATA
get_sc_log-0.1.3.dist-info/WHEEL
get_sc_log-0.1.3.dist-info/top_level.txt
get_sc_log-0.1.3.dist-info/RECORD
