Metadata-Version: 2.1
Name: get-sc-log
Version: 0.1.3
Summary: 查询日记
Home-page: UNKNOWN
Author: river
License: UNKNOWN
Platform: UNKNOWN
Requires-Dist: requests (>=2.0.0)
Requires-Dist: jsonpath (>=0.82)
